bitbake_language_server/__init__.py
bitbake_language_server/__main__.py
bitbake_language_server/_metainfo.py
bitbake_language_server/_version.py
bitbake_language_server/py.typed
bitbake_language_server/server.py
bitbake_language_server/utils.py
bitbake_language_server-0.0.15.data/data/share/bash-completion/completions/bitbake-language-server
bitbake_language_server-0.0.15.data/data/share/man/man1/bitbake-language-server.1
bitbake_language_server-0.0.15.data/data/share/zsh/site-functions/_bitbake-language-server
bitbake_language_server-0.0.15.dist-info/LICENSE
bitbake_language_server-0.0.15.dist-info/METADATA
bitbake_language_server-0.0.15.dist-info/WHEEL
bitbake_language_server-0.0.15.dist-info/entry_points.txt
bitbake_language_server-0.0.15.dist-info/top_level.txt
bitbake_language_server-0.0.15.dist-info/RECORD
