Metadata-Version: 2.1
Name: bitbake-language-server
Version: 0.0.15
Summary: bitbake language server
Author-email: Wu Zhenyu <wuzhenyu@ustc.edu>
License: GPL v3
Project-URL: Homepage, https://bitbake-language-server.readthedocs.io
Project-URL: Download, https://github.com/Freed-Wu/bitbake-language-server/releases
Project-URL: Bug Report, https://github.com/Freed-Wu/bitbake-language-server/issues
Project-URL: Source, https://github.com/Freed-Wu/bitbake-language-server
Classifier: Development Status :: 3 - Alpha
Classifier: Intended Audience :: Developers
Classifier: Topic :: Software Development :: Build Tools
Classifier: License :: OSI Approved :: GNU General Public License v3 (GPLv3)
Classifier: Operating System :: Microsoft :: Windows
Classifier: Operating System :: POSIX
Classifier: Operating System :: Unix
Classifier: Operating System :: MacOS
Classifier: Programming Language :: Python :: 3 :: Only
Classifier: Programming Language :: Python :: 3
Classifier: Programming Language :: Python :: 3.10
Classifier: Programming Language :: Python :: 3.11
Classifier: Programming Language :: Python :: 3.12
Classifier: Programming Language :: Python :: Implementation :: CPython
Classifier: Programming Language :: Python :: Implementation :: PyPy
Requires-Python: >=3.10
License-File: LICENSE
Requires-Dist: oelint-adv >=5.0.0
Requires-Dist: pygls
Provides-Extra: dev
Requires-Dist: pytest-cov ; extra == 'dev'
